{
  "tipo_do_documento": {
    "type": "macro",
    "precision": "44.67%",
    "recall": "45.65%",
    "f1-score": "45.16%",
    "accuracy": "35.00%"
  },
  "numero_do_processo_licitatorio": {
    "type": "non-macro",
    "accuracy": "63.00%",
    "recall": "63.00%",
    "precision": "63.00%",
    "f1-score": "63.00%"
  },
  "municipio": {
    "type": "macro",
    "precision": "92.75%",
    "recall": "92.75%",
    "f1-score": "92.75%",
    "accuracy": "95.00%"
  },
  "modalidade": {
    "type": "macro",
    "precision": "92.76%",
    "recall": "88.11%",
    "f1-score": "90.37%",
    "accuracy": "90.00%"
  },
  "formato_da_modalidade": {
    "type": "macro",
    "precision": "64.45%",
    "recall": "88.86%",
    "f1-score": "74.71%",
    "accuracy": "56.00%"
  },
  "numero_da_modalidade": {
    "type": "non-macro",
    "accuracy": "58.00%",
    "recall": "58.00%",
    "precision": "58.00%",
    "f1-score": "58.00%"
  },
  "objeto": {
    "type": "non-macro",
    "accuracy": "41.00%",
    "recall": "41.00%",
    "precision": "41.00%",
    "f1-score": "41.00%"
  },
  "data_de_abertura": {
    "type": "non-macro",
    "accuracy": "34.00%",
    "recall": "86.96%",
    "precision": "23.26%",
    "f1-score": "36.70%"
  },
  "site_do_edital": {
    "type": "non-macro",
    "accuracy": "40.00%",
    "recall": "64.52%",
    "precision": "25.00%",
    "f1-score": "36.04%"
  },
  "signatario": {
    "type": "non-macro",
    "accuracy": "67.00%",
    "recall": "74.42%",
    "precision": "66.67%",
    "f1-score": "70.33%"
  },
  "cargo_do_signatario": {
    "type": "non-macro",
    "accuracy": "66.00%",
    "recall": "74.42%",
    "precision": "65.98%",
    "f1-score": "69.95%"
  }
}